centiment_alpha/CMUTweetTagger.py
centiment_alpha/__init__.py
centiment_alpha/ark-tweet-nlp-0.3.2.jar
centiment_alpha/centiment.py
centiment_alpha/lexicon/GB1_S.lex
centiment_alpha/lexicon/README.txt
centiment_alpha/lexicon/contractions.replace
centiment_alpha/lexicon/corpus.v1.2.tweet
centiment_alpha/lexicon/emoji.lex
centiment_alpha/lexicon/emoticons.lex
centiment_alpha/lexicon/int_dictionary1.11.txt
centiment_alpha/lexicon/negation.list
centiment_alpha/lexicon/prefix.replace
centiment_alpha-0.0.33.dist-info/DESCRIPTION.rst
centiment_alpha-0.0.33.dist-info/METADATA
centiment_alpha-0.0.33.dist-info/RECORD
centiment_alpha-0.0.33.dist-info/WHEEL
centiment_alpha-0.0.33.dist-info/metadata.json
centiment_alpha-0.0.33.dist-info/top_level.txt
centiment_alpha-0.0.33.dist-info/zip-safe
