Metadata-Version: 2.0
Name: centiment-alpha
Version: 0.0.33
Summary: [alpha test] SO-CAL sentiment motified for tweets.
Home-page: UNKNOWN
Author: cchen224
Author-email: phantomkidding@gmail.com
License: MIT License
Keywords: SO-CAL
Platform: any
Requires-Dist: nltk
